sparrow/__init__.py
sparrow/__main__.py
sparrow/constant.py
sparrow/core.py
sparrow/version_ops.py
sparrow/ai_platform/__init__.py
sparrow/ai_platform/crawl.py
sparrow/ai_platform/metrics.py
sparrow/ai_platform/nlp_preprocess.py
sparrow/ai_platform/webpage_screen_shot.py
sparrow/api/__init__.py
sparrow/api/common.py
sparrow/api/fetch.py
sparrow/api/static/icon.png
sparrow/api/static/redoc.standalone.js
sparrow/api/static/swagger-ui-bundle.js
sparrow/api/static/swagger-ui.css
sparrow/async_api/__init__.py
sparrow/async_api/concurrent_call.py
sparrow/async_api/concurrent_executor.py
sparrow/async_api/core.py
sparrow/async_api/interface.py
sparrow/async_api/progress.py
sparrow/async_api/test_concurrent_executor.py
sparrow/cli/__init__.py
sparrow/cli/core.py
sparrow/cli/demo.py
sparrow/cli/downloader.py
sparrow/cli/git.py
sparrow/cli/mllm_run.py
sparrow/cli/script.py
sparrow/cli/tree.py
sparrow/color/__init__.py
sparrow/color/color.py
sparrow/color/constant.py
sparrow/cv/__init__.py
sparrow/cv/image.py
sparrow/cv/utils.py
sparrow/cv/video/__init__.py
sparrow/cv/video/key_frames.py
sparrow/cv/video/key_frames2.py
sparrow/cv/video/keyframes3.py
sparrow/datasets/__init__.py
sparrow/datasets/download.py
sparrow/datasets/fake_data.py
sparrow/debug/__init__.py
sparrow/decorators/__init__.py
sparrow/decorators/core.py
sparrow/dedup/__init__.py
sparrow/dedup/video.py
sparrow/distance/__init__.py
sparrow/distance/distance.py
sparrow/doc/__init__.py
sparrow/docker/__init__.py
sparrow/docker/nvidia_stat.py
sparrow/espec/__init__.py
sparrow/espec/app.py
sparrow/espec/date.py
sparrow/espec/especial.py
sparrow/extras/__init__.py
sparrow/extras/packages.py
sparrow/flow/__init__.py
sparrow/flow/executor1/__init__.py
sparrow/flow/executor1/executor.py
sparrow/functions/__init__.py
sparrow/functions/bezier.py
sparrow/functions/core.py
sparrow/functions/rate_function.py
sparrow/functions/utils.py
sparrow/git/__init__.py
sparrow/git/monitor.py
sparrow/helpers/metrics.py
sparrow_python-0.6.4.dist-info/METADATA
sparrow_python-0.6.4.dist-info/WHEEL
sparrow_python-0.6.4.dist-info/entry_points.txt
sparrow_python-0.6.4.dist-info/licenses/LICENSE
sparrow_python-0.6.4.dist-info/RECORD
